RuanjianshejiDeZhexueFix1/README.md
RuanjianshejiDeZhexueFix1/__init__.py
RuanjianshejiDeZhexueFix1/__main__.py
RuanjianshejiDeZhexueFix1/file.epub
RuanjianshejiDeZhexueFix1/index.html
RuanjianshejiDeZhexueFix1/css/__init__.py
RuanjianshejiDeZhexueFix1/css/annotations.css
RuanjianshejiDeZhexueFix1/css/main.css
RuanjianshejiDeZhexueFix1/css/normalize.css
RuanjianshejiDeZhexueFix1/css/popup.css
RuanjianshejiDeZhexueFix1/font/__init__.py
RuanjianshejiDeZhexueFix1/font/fontello.eot
RuanjianshejiDeZhexueFix1/font/fontello.svg
RuanjianshejiDeZhexueFix1/font/fontello.ttf
RuanjianshejiDeZhexueFix1/font/fontello.woff
RuanjianshejiDeZhexueFix1/img/__init__.py
RuanjianshejiDeZhexueFix1/img/annotator-glyph-sprite.png
RuanjianshejiDeZhexueFix1/img/annotator-icon-sprite.png
RuanjianshejiDeZhexueFix1/img/apple-touch-icon.png
RuanjianshejiDeZhexueFix1/img/cancelfullscreen.png
RuanjianshejiDeZhexueFix1/img/close.png
RuanjianshejiDeZhexueFix1/img/fullscreen.png
RuanjianshejiDeZhexueFix1/img/loader.gif
RuanjianshejiDeZhexueFix1/img/menu-icon.png
RuanjianshejiDeZhexueFix1/img/save.png
RuanjianshejiDeZhexueFix1/img/saved.png
RuanjianshejiDeZhexueFix1/img/settings-s.png
RuanjianshejiDeZhexueFix1/img/settings.png
RuanjianshejiDeZhexueFix1/img/star.png
RuanjianshejiDeZhexueFix1/js/__init__.py
RuanjianshejiDeZhexueFix1/js/epub.js
RuanjianshejiDeZhexueFix1/js/epub.min.js
RuanjianshejiDeZhexueFix1/js/epub.min.map
RuanjianshejiDeZhexueFix1/js/hooks.min.js
RuanjianshejiDeZhexueFix1/js/hooks.min.map
RuanjianshejiDeZhexueFix1/js/reader.js
RuanjianshejiDeZhexueFix1/js/reader.js.map
RuanjianshejiDeZhexueFix1/js/reader.min.js
RuanjianshejiDeZhexueFix1/js/reader.min.map
RuanjianshejiDeZhexueFix1/js/hooks/__init__.py
RuanjianshejiDeZhexueFix1/js/hooks/extensions/__init__.py
RuanjianshejiDeZhexueFix1/js/hooks/extensions/highlight.js
RuanjianshejiDeZhexueFix1/js/libs/__init__.py
RuanjianshejiDeZhexueFix1/js/libs/jquery.min.js
RuanjianshejiDeZhexueFix1/js/libs/localforage.min.js
ruanjiansheji_de_zhexue_fix1-2025.3.24.1.dist-info/METADATA
ruanjiansheji_de_zhexue_fix1-2025.3.24.1.dist-info/WHEEL
ruanjiansheji_de_zhexue_fix1-2025.3.24.1.dist-info/entry_points.txt
ruanjiansheji_de_zhexue_fix1-2025.3.24.1.dist-info/top_level.txt
ruanjiansheji_de_zhexue_fix1-2025.3.24.1.dist-info/RECORD
